HiveClients/HiveClients.py
HiveClients/__init__.py
hiveclients-1.0.2.dist-info/METADATA
hiveclients-1.0.2.dist-info/WHEEL
hiveclients-1.0.2.dist-info/top_level.txt
hiveclients-1.0.2.dist-info/RECORD
