Metadata-Version: 2.4
Name: HiveClients
Version: 1.0.2
Summary: 链接hive数据库的程序,使用impala库
Author: DongYang
Author-email: 649898871@qq.com
Requires-Dist: thrift<1.0.0,>=0.13.0
Requires-Dist: impyla<1.0.0,>=0.15.0
Requires-Dist: pandas<3.0.0,>=1.0.0
